Metadata-Version: 2.1
Name: pynotificator
Version: 0.4.1
Summary: pynotificator: Python から様々な通知を簡単に送るためのライブラリ
Home-page: https://github.com/higurashi-takuto/pynotificator
Author: higurashi-takuto
Author-email: contact@hgrs.me
License: MIT
Platform: UNKNOWN
